pyroomos/__init__.py
pyroomos/xCommand.py
pyRoomOSxAPI-0.1.dist-info/LICENSE
pyRoomOSxAPI-0.1.dist-info/METADATA
pyRoomOSxAPI-0.1.dist-info/WHEEL
pyRoomOSxAPI-0.1.dist-info/top_level.txt
pyRoomOSxAPI-0.1.dist-info/RECORD
