Metadata-Version: 2.1
Name: pyRoomOSxAPI
Version: 0.1
Summary: Simple implementation RoomOS xAPI
Home-page: https://github.com/batonogov/pyRoomOSxAPI
Author: Fedor Batonogov
Author-email: batonogov@icloud.com
Classifier: Programming Language :: Python :: 3.10
Classifier: License :: OSI Approved :: MIT License
Classifier: Operating System :: OS Independent
Requires-Python: >=3.10
License-File: LICENSE
